pyzill/__init__.py
pyzill/details.py
pyzill/parse.py
pyzill/search.py
pyzill/utils.py
pyzill-1.0.3.dist-info/licenses/LICENSE
pyzill-1.0.3.dist-info/METADATA
pyzill-1.0.3.dist-info/WHEEL
pyzill-1.0.3.dist-info/top_level.txt
pyzill-1.0.3.dist-info/RECORD
