Metadata-Version: 2.4
Name: pyzill
Version: 1.0.3
Summary: Zillow scraper in Python
Author-email: John Balvin <johnchristian@hotmail.es>
License: MIT
Project-URL: Homepage, https://github.com/johnbalvin/pyzill
Keywords: zillow,scraper,crawler
License-File: LICENSE
Requires-Dist: bs4
Requires-Dist: requests
Requires-Dist: curl_cffi
Dynamic: license-file
